pysem/__init__.py
pysem/data.py
pysem/glosses.py
pysem/sense.py
pysem/data/concepticon.zip
pysem/data/sense.csv
pysem-1.2.1.dist-info/licenses/LICENSE
pysem-1.2.1.dist-info/METADATA
pysem-1.2.1.dist-info/WHEEL
pysem-1.2.1.dist-info/entry_points.txt
pysem-1.2.1.dist-info/top_level.txt
pysem-1.2.1.dist-info/RECORD
